{
    "@class": "com.kony.gen.viz.model.component.KVizImage2",
    "DNDConfig": null,
    "__parentReadjusting__": false,
    "_base64_": null,
    "_height_": {
        "type": "string",
        "value": "100%"
    },
    "_left_": {
        "type": "string",
        "value": "80%"
    },
    "_margin_": [
        0,
        0,
        0,
        0
    ],
    "_padding_": [
        0,
        0,
        0,
        0
    ],
    "_skin_": "s56010331e3441eebea3dd23ec9b28af",
    "_src_": "imagedrag.png",
    "_top_": {
        "type": "string",
        "value": "10%"
    },
    "_width_": {
        "type": "string",
        "value": "15%"
    },
    "canUpdateUI": true,
    "containerId": true,
    "containerweight": 100,
    "context": {
        "channel": "desktop",
        "platform": "desktopweb",
        "templateType": "segments",
        "topLevelBox": null
    },
    "id": "imgFloorMap",
    "imagescalemode": 1,
    "info": null,
    "isvisible": true,
    "kuid": "7dab5a20fe314cc6ae9b15bf7f8032c5",
    "name": "kony.ui.Image2",
    "parent": "segFloorMaps",
    "pf": "tempfloorplans",
    "srcType": 1,
    "wType": "Image",
    "widgetalignment": 5,
    "zindex": 1
}