{
    "AS_Button_0bc0fa68a99b46e69df6ff8c4e1adf96": {
        "id": "AS_Button_0bc0fa68a99b46e69df6ff8c4e1adf96",
        "type": "ACTION_SEQUENCE",
        "params": [{
            "datatype": "collection",
            "name": "eventobject"
        }],
        "contextObj": {
            "name": "frmHome",
            "type": "forms",
            "platform": "",
            "KUID": "02b526b03d634e6d87abc62d59722cc4"
        },
        "actions": [{
            "id": "ADD_SNIPPET__b607c89df4fc4b3eb1576bc7b74f6482",
            "type": "ADD_SNIPPET",
            "codeSnippet": "getEvents();",
            "parentId": null,
            "callbackType": null
        }]
    }
}